{
  "$id": "1",
  "HistorialDeChats": {
    "$id": "2",
    "2100989690": {
      "$id": "3",
      "MensajesDelUser": {
        "$id": "4",
        "$values": [
          "/invitarempresa",
          "Pelispedia"
        ]
      },
      "MensajesDelUserReves": {
        "$id": "5",
        "$values": [
          "Pelispedia",
          "/invitarempresa"
        ]
      }
    },
    "2124515755": {
      "$id": "6",
      "MensajesDelUser": {
        "$id": "7",
        "$values": [
          "/verubicacion",
          "/verubicacionempresa"
        ]
      },
      "MensajesDelUserReves": {
        "$id": "8",
        "$values": [
          "/verubicacionempresa",
          "/verubicacion"
        ]
      }
    }
  },
  "EmpresasInvitadas": {
    "$id": "9",
    "$values": [
      {
        "$id": "10",
        "FechaOfertasEntregadas": {
          "$id": "11"
        },
        "HabilitacionesEmpresa": {
          "$id": "12",
          "$values": []
        },
        "InteresadosEnOfertas": {
          "$id": "13",
          "$values": []
        },
        "OfertasAceptadas": {
          "$id": "14",
          "$values": []
        },
        "MisOfertas": {
          "$id": "15",
          "$values": []
        },
        "Nombre": "conaprole",
        "Ubicacion": {
          "$id": "16",
          "NombreCalle": "pakistan"
        },
        "Rubro": {
          "$id": "17",
          "Nombre": "Textil"
        }
      },
      {
        "$id": "18",
        "FechaOfertasEntregadas": {
          "$id": "19"
        },
        "HabilitacionesEmpresa": {
          "$id": "20",
          "$values": [
            {
              "$id": "21",
              "Nombre": "APA"
            }
          ]
        },
        "InteresadosEnOfertas": {
          "$id": "22",
          "$values": []
        },
        "OfertasAceptadas": {
          "$id": "23",
          "$values": []
        },
        "MisOfertas": {
          "$id": "24",
          "$values": [
            {
              "$id": "25",
              "HabilitacionesOferta": {
                "$id": "26",
                "$values": []
              },
              "Interesado": {
                "$id": "27",
                "$values": []
              },
              "Nombre": "LECHEDELABUENA",
              "Material": {
                "$id": "28",
                "Tipo": "Reciclado",
                "Cantidad": "20",
                "Precio": "100",
                "Unidad": "Litros"
              },
              "Tags": "LaMejor",
              "Ubicacion": {
                "$id": "29",
                "NombreCalle": "Av. 8 de Octubre 1921"
              },
              "EmpresaCreadora": {
                "$ref": "18"
              },
              "ConstantesPuntuales": "Constante",
              "FechaDePublicacion": "2021-11-30T18:28:52.3613463-03:00"
            }
          ]
        },
        "Nombre": "Pelispedia",
        "Ubicacion": {
          "$id": "30",
          "NombreCalle": "Comandante Braga"
        },
        "Rubro": {
          "$ref": "17"
        }
      },
      {
        "$ref": "18"
      }
    ]
  },
  "Emprendedores": {
    "$id": "31"
  },
  "Empresas": {
    "$id": "32",
    "2124515755": {
      "$ref": "18"
    }
  },
  "Publicaciones": {
    "$id": "33",
    "OfertasPublicados": {
      "$id": "34",
      "$values": [
        {
          "$ref": "25"
        }
      ]
    }
  },
  "ContenedorRubrosHabs": {
    "$id": "35",
    "ListaRubros": {
      "$id": "36",
      "$values": [
        {
          "$ref": "17"
        },
        {
          "$id": "37",
          "Nombre": "Metalurgia"
        },
        {
          "$id": "38",
          "Nombre": "Electrodom\u00E9sticos"
        }
      ]
    },
    "ListaHabilitaciones": {
      "$id": "39",
      "$values": [
        {
          "$id": "40",
          "Nombre": "APA"
        },
        {
          "$id": "41",
          "Nombre": "ISO"
        },
        {
          "$id": "42",
          "Nombre": "SOA"
        }
      ]
    }
  },
  "BuscadorUbicacion": {
    "$id": "43"
  },
  "BuscadorTags": {
    "$id": "44"
  },
  "BuscadorMaterial": {
    "$id": "45"
  },
  "PrinterConsola": {
    "$id": "46"
  },
  "ListaNombreOfertas": {
    "$id": "47",
    "$values": [
      "LECHEDELABUENA"
    ]
  },
  "Administradores": {
    "$id": "48",
    "2100989690": {
      "$id": "49",
      "Nombre": "Adminxito",
      "Empresas": {
        "$id": "50",
        "$values": [
          {
            "$ref": "18"
          }
        ]
      }
    }
  }
}